Workbook

Sheet Oxu
A1: GRC360 — Azərbaycan qanunları üzrə nümunə öhdəlik kitabxanası
A2: Bu fayl nümunədir: hər öhdəlik qanunun rəsmi mətnindən sitatla (verbatim) və maddə nömrəsi ilə çıxarılıb. İstifadədən əvvəl hüquqşünas tərəfindən yoxlanmalıdır; bu hüquqi məsləhət deyil.
A4: Vərəqlər
A5: Mənbələr — qanun və qaydalar, rəsmi nömrə, tarix, nəzarət orqanı və mətnin götürüldüyü link.
A6: Öhdəliklər — hər sətir bir öhdəlik: maddə, rəsmi mətndən sitat, sadə dildə öhdəlik (AZ/EN), kimə aiddir, tezlik/son tarix, risk, təklif olunan control-lar və policy-lər.
A7: Policy-lər — bu qanunlara görə şirkətdə olmalı daxili siyasət və prosedurlar, hansı maddələrdən irəli gəlir.
A8: Xülasə — qanun və risk səviyyəsinə görə saylar (düsturla hesablanır).
A9: Qeydlər — mətnləri çıxararkən qarşılaşılan məhdudiyyətlər və yoxlanmalı məqamlar.
A11: GRC360-a import
A12: Yanındakı GRC360-obligations-import.csv faylı Compliance Hub › Obligations › Import CSV ilə birbaşa yüklənir (sütunlar: legalActName, articleOrClauseNo, category, requirementDescription, regulatoryAuthority, status, riskLevel). Bütün öhdəliklər 'Under Review' statusu ilə gəlir; Responsible Team import-dan sonra təyin edilir.
A14: Sütunlar haqqında
A15: Risk — pozuntunun mümkün nəticəsinə görə ilkin qiymətləndirmədir (Yüksək / Orta / Aşağı); şirkət öz kontekstinə görə dəyişməlidir.
A16: '(yoxlanmalı)' qeydi olan dəyərlər mənbədə birbaşa təsdiqlənməyib.

Sheet Mənbələr
A1: Qısa ad | B1: Rəsmi ad | C1: Nömrə və tarix | D1: Nəzarət orqanı | E1: Status | F1: Qüvvəyə minmə | G1: Versiya / son dəyişiklik | H1: Mənbə linki
A2: Fərdi məlumatlar haqqında Qanun | B2: Azərbaycan Respublikasının "Fərdi məlumatlar haqqında" Qanunu | C2: 998-IIIQ, 2010-05-11 | D2: Rəqəmsal İnkişaf və Nəqliyyat Nazirliyi (qanunda: 'müvafiq icra hakimiyyəti orqanı'; konkret orqan Prezident fərmanları ilə müəyyən edilir) (yoxlanmalı) | E2: Qüvvədədir | G2: 28.06.2024, № 1193-VIQD (dərc: AZƏRTAC 16.07.2024; Qanunvericilik Toplusu 2024, № 7, maddə 769) | H2: https://e-qanun.az/frameworks/19/f_19675.html
A3: İnformasiya Qanunu | B3: “İnformasiya, informasiyalaşdırma və informasiyanın mühafizəsi haqqında” Azərbaycan Respublikasının Qanunu | C3: 460-IQ, 1998-04-03 | D3: Milli CERT — Milli Kibertəhlükəsizlik Agentliyi qismində Rəqəmsal İnkişaf və Nəqliyyat Nazirliyi (Fərman № 729, b. 2.9, 10.08.2026 № 761 Fərmanı ilə); maliyyə bazarı subyektləri üçün AMB koordinasiyası | E3: Qüvvədədir (e-qanun.az) | G3: 454-VIIQD, 14.07.2026 (AZƏRTAC 10.08.2026; “Azərbaycan” qəzeti 11.08.2026, № 142) — V-II fəsil “İnformasiya infrastrukturunun informasiya təhlükəsizliyi və kibertəhlükəsizliyi” (20-7 – 20-12) əlavə edilib | H3: https://e-qanun.az/framework/3525
A4: Elektron İmza Qanunu | B4: “Elektron imza və elektron sənəd haqqında” Azərbaycan Respublikasının Qanunu | C4: 602-IIQ, 2004-03-09 | D4: Rəqəmsal İnkişaf və Nəqliyyat Nazirliyi (Prezidentin 26.05.2004 № 65 Fərmanı, b. 2.3); texniki təhlükəsizlik monitorinqi — RİNN və DTX (b. 2.5) | E4: Qüvvədədir (e-qanun.az) | G4: 1048-VIQD, 05.12.2023 (AZƏRTAC 25.12.2023) — 1.1.15 “elektron sənəd” anlayışı yeni redaksiyada | H4: https://e-qanun.az/framework/5916
A5: KİI Qaydaları (NK № 229) / İnformasiya Qanunu V-I fəsil | B5: “Azərbaycan Respublikasında kritik informasiya infrastrukturunun təhlükəsizliyinin təmin edilməsi qaydaları”nın təsdiq edilməsi haqqında Azərbaycan Respublikası Nazirlər Kabinetinin Qərarı | C5: 229, 2023-07-17 | D5: Dövlət Təhlükəsizliyi Xidməti (səlahiyyətli orqan; Milli kibermərkəz) — dövlət qurumlarına münasibətdə XRİTDX ilə birgə (Fərman № 1315, b. 1; Qaydalar b. 1.2) | E5: Qüvvədədir (e-qanun.az) | G5: NK-nin 02.12.2023 № 431 Qərarı (5.1, 7.5 redaksiyası; yeni 8.4.3-1) | H5: https://e-qanun.az/framework/54651
A6: Səlahiyyətli orqanları müəyyən edən aktlar | B6: Səlahiyyətli orqanları müəyyən edən aktlar | E6: Qüvvədədir | H6: https://e-qanun.az/framework/3605
A7: CBAR İnformasiya təhlükəsizliyi Tələbləri (14/2) | B7: Maliyyə bazarlarında fəaliyyətinə nəzarət edilən subyektlərdə informasiya təhlükəsizliyinin təmin edilməsinə dair Tələblər | C7: Azərbaycan Respublikası Mərkəzi Bankı İdarə Heyətinin Qərarı № 14/2, 2024-03-28 | D7: Azərbaycan Respublikasının Mərkəzi Bankı | E7: Qüvvədədir (in force) per e-qanun.az metadata, checked 2026-10-15 | F7: 2025-04-09 | G7: Original text as published on e-qanun.az (no amendment footnotes present in the published HTML as of 2026-10-15) | H7: https://e-qanun.az/frameworks/56/f_56708.html
A8: Banklarda informasiya təhlükəsizliyinin idarə edilməsi Qaydası (20/1) — LƏĞV EDİLİB | B8: Banklarda informasiya təhlükəsizliyinin idarə edilməsi Qaydası | C8: Azərbaycan Respublikası Mərkəzi Bankı İdarə Heyətinin Qərarı № 20/1, 2021-07-14 | D8: Azərbaycan Respublikasının Mərkəzi Bankı | E8: REPEALED: the Rules (Part 1 of Decision 20/1) were repealed by Decision 14/2 of 28.03.2024 with effect from 09.04.2025 (14/2 Part 2; e-qanun footnote [1] on 20/1). e-qanun still shows the decision record as 'Qüvvədədir' because only Part 1 was repealed. | F8: 2022-04-01 | G8: Historical text only (cbar.az PDF of original 2021 decision; e-qanun f_48025.html with repeal footnote) | H8: https://uploads.cbar.az/assets/8de89476ebb3fc1e60c61555e.pdf

Sheet Öhdəliklər
A1: ID | B1: Kateqoriya | C1: Qanun / qayda | D1: Maddə / bənd | E1: Öhdəlik (AZ) | F1: Obligation (EN) | G1: Rəsmi mətn (sitat) | H1: Kimə aiddir | I1: Növ | J1: Tezlik / son tarix | K1: Risk | L1: Nəzarət orqanı | M1: Təklif olunan control-lar | N1: Əlaqəli policy-lər | O1: Mənbə
A2: PD-01 | B2: Fərdi məlumatlar | C2: Fərdi məlumatlar haqqında Qanun | D2: Maddə 9.6 | E2: Hər emal fəaliyyəti üçün qanuni əsası (razılıq, açıq məlumat, qanun, həyat/sağlamlıq) müəyyənləşdirin və sənədləşdirin. | F2: Identify and document a lawful basis (consent, public data, law, vital interest) for every processing activity. | G2: 9.6. Fərdi məlumatların toplanılması və işlənilməsi yalnız aşağıdakı şərtlərdən biri olduqda həyata keçirilə bilər: 9.6.1. subyekt fərdi məlumatların toplanılmasına və işlənilməsinə öz razılığını verdikdə və ya bu məlumatlar açıq kateqoriyalı olduqda; 9.6.2. fərdi məlumatlar onların toplanılması və işlənilməsi məqsədlərini və üsullarını müəyyən edən qanunvericilik əsasında işlənildikdə; […] 9.6.4. fərdi məlumatların toplanılması və işlənilməsi subyektin həyat və sağlamlığını qorumaq üçün lazım olduqda. | H2: Fərdi məlumatların mülkiyyətçisi və operatoru (dövlət/yerli özünüidarə orqanları, hüquqi və fiziki şəxslər; şəxsi/ailə ehtiyacları istisna — 3.3) | I2: Legal | J2: ongoing (hər yeni emal fəaliyyətindən əvvəl) | K2: Yüksək | L2: Rəqəmsal İnkişaf və Nəqliyyat Nazirliyi (qanunda: 'müvafiq icra hakimiyyəti orqanı'; konkret orqan Prezident fərmanları ilə müəyyən edilir) (yoxlanmalı) | M2: • Emal fəaliyyətləri reyestrində hər fəaliyyət üçün hüquqi əsas sahəsi • Yeni layihələrdə məxfilik qiymətləndirməsi (privacy-by-design checklist) • Hüquq şöbəsinin hüquqi əsası təsdiqləməsi | N2: • Fərdi məlumatların mühafizəsi siyasəti • Emal fəaliyyətlərinin reyestri proseduru | O2: https://e-qanun.az/frameworks/19/f_19675.html
A3: PD-02 | B3: Fərdi məlumatlar | C3: Fərdi məlumatlar haqqında Qanun | D3: Maddə 8.1, 8.2 | E3: Razılığı yazılı (və ya gücləndirilmiş e-imza ilə) alın; formaya 8.2-də tələb olunan bütün elementləri daxil edin. | F3: Obtain consent in writing (or with qualified e-signature) and include all elements required by Art. 8.2. | G3: 8.1. Azərbaycan Respublikasının qanunvericiliyi ilə müəyyən olunmuş qaydada fərdi məlumatların məcburi şəkildə toplanılması və işlənilməsi halları istisna olmaqla, hər hansı şəxs barəsində fərdi məlumatların toplanılmasına və işlənilməsinə yalnız subyekt tərəfindən verilmiş yazılı, o cümlədən gücləndirilmiş elektron imzalı elektron sənəd formasında razılıq və ya özünün yazılı təqdim etdiyi məlumatlar əsasında yol verilir. 8.2. Subyektin fərdi məlumatların işlənilməsi üçün yazılı (o cümlədən Elektron Hökumət İnformasiya Sistemi üzərindən) razılığına aşağıdakılar daxil edilməlidir:[3] 8.2.1. subyektin kimliyini müəyyənləşdirməyə imkan verən məlumatlar; 8.2.2. subyektdən razılıq alan mülkiyyətçinin və ya operatorun kimliyini müəyyənləşdirməyə imkan verən məlumatlar; 8.2.3. fərdi məlumatların toplanılması və işlənilməsi məqsədi; 8.2.4. subyekt tərəfindən işlənilməsinə razılıq verilmiş fərdi məlumatların və onların işlənilmə əməliyyatlarının siyahıları; 8.2.5. subyektin razılığının qüvvədə olma dövrü və onun geri götürülməsi şərtləri; | H3: Fərdi məlumatların mülkiyyətçisi və operatoru (dövlət/yerli özünüidarə orqanları, hüquqi və fiziki şəxslər; şəxsi/ailə ehtiyacları istisna — 3.3) | I3: Legal | J3: on event (məlumat toplanmazdan əvvəl) | K3: Yüksək | L3: Rəqəmsal İnkişaf və Nəqliyyat Nazirliyi (qanunda: 'müvafiq icra hakimiyyəti orqanı'; konkret orqan Prezident fərmanları ilə müəyyən edilir) (yoxlanmalı) | M3: • Standart razılıq forması şablonu (8.2.1–8.2.6 elementləri ilə) • Razılıq formalarının hüquqi baxışı • Yetkinlik yaşına çatmayanlar üçün valideyn/qanuni nümayəndə razılığı (8.3) | N3: • Razılığın idarə edilməsi proseduru • Məxfilik bildirişi (subyektin məlumatlandırılması) | O3: https://e-qanun.az/frameworks/19/f_19675.html
A4: PD-03 | B4: Fərdi məlumatlar | C4: Fərdi məlumatlar haqqında Qanun | D4: Maddə 8.4, 8.6 | E4: Razılığın sübutunu saxlayın; razılığın alınması və geri çağırılmasını Elektron Hökumət İnformasiya Sistemi üzərindən təmin edin. | F4: Retain evidence of consent; handle consent collection and withdrawal through the e-Government Information System. | G4: 8.4. Subyektdən onun fərdi məlumatlarının toplanılması və işlənilməsi üçün razılığın alınması haqqında sübutun təqdim olunması vəzifəsi mülkiyyətçinin və ya operatorun üzərinə düşür. […] 8.6. Bu Qanunun 3.2-ci maddəsində qeyd edilən hallar, habelə Azərbaycan Respublikasının normativ hüquqi aktları ilə müəyyən olunmuş qaydada fərdi məlumatların məcburi şəkildə toplanılması və işlənilməsi istisna olmaqla, fərdi məlumatların toplanılmasına və işlənilməsinə subyektlərin razılığının alınması və geri çağırılması mərkəzləşdirilmiş qaydada Elektron Hökumət İnformasiya Sistemi üzərindən təmin edilir. | H4: Fərdi məlumatların mülkiyyətçisi və operatoru (dövlət/yerli özünüidarə orqanları, hüquqi və fiziki şəxslər; şəxsi/ailə ehtiyacları istisna — 3.3) | I4: Legal | J4: ongoing | K4: Orta | L4: Rəqəmsal İnkişaf və Nəqliyyat Nazirliyi (qanunda: 'müvafiq icra hakimiyyəti orqanı'; konkret orqan Prezident fərmanları ilə müəyyən edilir) (yoxlanmalı) | M4: • Razılıq jurnalı (kim, nə vaxt, hansı versiya, kanal) • EHİS (e-gov) razılıq inteqrasiyası və ya prosedur • Razılıq qeydlərinin saxlanma müddəti | N4: • Razılığın idarə edilməsi proseduru | O4: https://e-qanun.az/frameworks/19/f_19675.html
A5: PD-04 | B5: Fərdi məlumatlar | C5: Fərdi məlumatlar haqqında Qanun | D5: Maddə 9.1, 9.2, 9.3, 11.1 | E5: Məqsədi əvvəlcədən bəyan edin, yalnız zəruri məlumatları toplayın, məlumatları dəqiq və aktual saxlayın. | F5: Declare purposes in advance, collect only necessary data, and keep data accurate and up to date. | G5: Fərdi məlumatlar yalnız qanuni, əvvəlcədən müəyyən olunmuş və bəyan edilmiş məqsədlər üçün toplanılmalı və göstərilmiş məqsədlərə uyğun üsullarla işlənilməlidir. 9.2. Toplanılan və işlənilən fərdi məlumatların həcmi və xarakteri bəyan edilmiş məqsədlərə və mülkiyyətçilərin səlahiyyətlərinə uyğun olmalıdır. 9.3. Fərdi məlumatlar dəqiq, tam olmalı və zərurət yarandıqda təzələnməlidir. […] 11.1. Mülkiyyətçi və ya operator subyektdən yalnız işlənilmə məqsədlərinə nail olmaq üçün zəruri olan fərdi məlumatları almaq hüququna malikdir. | H5: Fərdi məlumatların mülkiyyətçisi və operatoru (dövlət/yerli özünüidarə orqanları, hüquqi və fiziki şəxslər; şəxsi/ailə ehtiyacları istisna — 3.3) | I5: Legal | J5: ongoing | K5: Orta | L5: Rəqəmsal İnkişaf və Nəqliyyat Nazirliyi (qanunda: 'müvafiq icra hakimiyyəti orqanı'; konkret orqan Prezident fərmanları ilə müəyyən edilir) (yoxlanmalı) | M5: • Formalarda sahələrin zərurilik baxışı (data minimisation review) • Məlumat keyfiyyəti/yeniləmə proseduru • Məqsəd dəyişikliyində yenidən qiymətləndirmə | N5: • Fərdi məlumatların mühafizəsi siyasəti • Emal fəaliyyətlərinin reyestri proseduru | O5: https://e-qanun.az/frameworks/19/f_19675.html
A6: PD-05 | B6: Fərdi məlumatlar | C6: Fərdi məlumatlar haqqında Qanun | D6: Maddə 9.4 | E6: Məqsədə nail olunduqda və saxlanma zərurəti aradan qalxdıqda fərdi məlumatları təxirə salınmadan məhv edin. | F6: Destroy personal data without delay once the purpose is achieved and retention is no longer necessary. | G6: 9.4. Fərdi məlumatların toplanılması və işlənilməsi məqsədlərinə nail olunduqda və onların saxlanılması zərurəti aradan qalxdıqda həmin məlumatlar təxirə salınmadan məhv edilməlidir. | H6: Fərdi məlumatların mülkiyyətçisi və operatoru (dövlət/yerli özünüidarə orqanları, hüquqi və fiziki şəxslər; şəxsi/ailə ehtiyacları istisna — 3.3) | I6: Legal | J6: on event (məqsəd bitdikdə — təxirə salınmadan) + periodik baxış | K6: Orta | L6: Rəqəmsal İnkişaf və Nəqliyyat Nazirliyi (qanunda: 'müvafiq icra hakimiyyəti orqanı'; konkret orqan Prezident fərmanları ilə müəyyən edilir) (yoxlanmalı) | M6: • Məlumat kateqoriyaları üzrə saxlanma cədvəli • Avtomatik silmə/arxivləşdirmə qaydaları • Məhvetmə aktları (protokol) və təsdiq | N6: • Məlumatların saxlanması və məhv edilməsi siyasəti | O6: https://e-qanun.az/frameworks/19/f_19675.html
A7: PD-06 | B7: Fərdi məlumatlar | C7: Fərdi məlumatlar haqqında Qanun | D7: Maddə 9.7, 9.8 | E7: Xüsusi kateqoriyalı məlumatları (irq, din, səhhət, məhkumluq və s.) yalnız 9.7 istisnaları ilə emal edin; əsas aradan qalxdıqda bloklayın/məhv edin. | F7: Process special-category data only under Art. 9.7 exceptions; block/destroy it once the ground ceases. | G7: 9.7. Xüsusi kateqoriyalı məlumatların toplanılmasına və işlənilməsinə, aşağıdakı hallar istisna olmaqla, yol verilmir: 9.7.1. xüsusi kateqoriyalı məlumatların toplanılması və işlənilməsi qanunla müəyyən olunmuş hallarda məcburi xarakter daşıdıqda; 9.7.1-1. subyektin yazılı (o cümlədən Elektron Hökumət İnformasiya Sistemi üzərindən) razılığı olduqda; […] 9.8. Bu Qanunun 9.7-ci maddəsində nəzərdə tutulmuş hallarda xüsusi kateqoriyalı məlumatların toplanılması və işlənilməsi səbəbləri aradan qaldırıldıqda həmin məlumatlara dərhal qadağan qoyulmalı, xüsusi kateqoriyalı məlumatların subyekti həmin məlumatların informasiya sistemində saxlanmasına və ya arxivə verilməsinə razılıq vermədikdə bu məlumatlar təxirə salınmadan məhv edilməlidir. | H7: Fərdi məlumatların mülkiyyətçisi və operatoru (dövlət/yerli özünüidarə orqanları, hüquqi və fiziki şəxslər; şəxsi/ailə ehtiyacları istisna — 3.3) | I7: Legal | J7: ongoing; on event (əsas aradan qalxdıqda — dərhal) | K7: Yüksək | L7: Rəqəmsal İnkişaf və Nəqliyyat Nazirliyi (qanunda: 'müvafiq icra hakimiyyəti orqanı'; konkret orqan Prezident fərmanları ilə müəyyən edilir) (yoxlanmalı) | M7: • Xüsusi kateqoriyalı məlumatların inventarı • Ayrıca yazılı razılıq forması • Gücləndirilmiş giriş məhdudiyyəti və şifrələmə | N7: • Xüsusi kateqoriyalı və biometrik məlumatların emalı proseduru • Məlumatların saxlanması və məhv edilməsi siyasəti | O7: https://e-qanun.az/frameworks/19/f_19675.html
A8: PD-07 | B8: Fərdi məlumatlar | C8: Fərdi məlumatlar haqqında Qanun | D8: Maddə 9.5 | E8: Biometrik məlumatlara (barmaq izi, üz təsviri, səs və s.) qanunun bütün emal şərtlərini tam həcmdə tətbiq edin. | F8: Apply all processing conditions of the Law in full to biometric data (fingerprints, face images, voice, etc.). | G8: 9.5. Fərdi məlumatların bu Qanunla müəyyən olunmuş toplanılması və işlənilməsi şərtləri insan orqanizminin bioloji xüsusiyyətlərini səciyyələndirən və onun kimliyini birmənalı olaraq müəyyənləşdirməyə imkan verən məlumatların – əl-barmaq və ovuc izləri, üz təsviri, gözün qüzehli və tor qişası, səs fraqmenti və onun akustik parametrləri, dezoksiribonuklein turşusu (DNT) analizinin nəticələri, bədən ölçüləri, bədənin xüsusi əlamətlərinin və fiziki çatışmazlıqlarının təsviri, yazı xətti və imzası, habelə digər biometrik məlumatların toplanılmasına və işlənilməsinə tam həcmdə şamil edilir. | H8: Fərdi məlumatların mülkiyyətçisi və operatoru (dövlət/yerli özünüidarə orqanları, hüquqi və fiziki şəxslər; şəxsi/ailə ehtiyacları istisna — 3.3) | I8: Legal | J8: ongoing | K8: Orta | L8: Rəqəmsal İnkişaf və Nəqliyyat Nazirliyi (qanunda: 'müvafiq icra hakimiyyəti orqanı'; konkret orqan Prezident fərmanları ilə müəyyən edilir) (yoxlanmalı) | M8: • Biometrik sistemlərin (giriş-nəzarət, FaceID, səs qeydi) inventarı • Biometrik emal üçün ayrıca razılıq və məlumatlandırma • Biometrik şablonların şifrələnməsi | N8: • Xüsusi kateqoriyalı və biometrik məlumatların emalı proseduru | O8: https://e-qanun.az/frameworks/19/f_19675.html
A9: PD-08 | B9: Fərdi məlumatlar | C9: Fərdi məlumatlar haqqında Qanun | D9: Maddə 11.2, 11.3 | E9: Toplama zamanı subyektə kimliyinizi, məqsədi və əsasını, mühafizə səviyyəsini, sertifikat/ekspertiza, alıcıları və hüquqlarını bildirin. | F9: At collection, inform subjects of your identity, purpose and basis, protection level, certification/expertise, recipients and rights. | G9: 11.2. Mülkiyyətçi və ya operator fərdi məlumatları toplayarkən subyektə aşağıdakıları mütləq bildirməlidir: 11.2.1. mülkiyyətçinin və ya operatorun kimliyini müəyyənləşdirən məlumatlar; 11.2.2. fərdi məlumatların işlənilmə məqsədi və bu məqsədin hüquqi cəhətdən əsaslandırılması; 11.2.3. toplanılan və işlənilən fərdi məlumatların informasiya sistemində mühafizə səviyyəsi; 11.2.4. informasiya sistemlərinin uyğunluq sertifikatının mövcudluğu və dövlət ekspertizasından keçirilməsi haqqında məlumat; 11.2.5. fərdi məlumatların nəzərdə tutulan istifadəçilərinin, o cümlədən məlumat mübadiləsi aparılması nəzərdə tutulan informasiya sisteminin dairəsi; 11.2.6. subyektin bu Qanunla müəyyən olunmuş hüquqları barədə məlumatlar. 11.3. Fərdi məlumatların təqdim olunması qanunla müəyyən olunmuşdursa, mülkiyyətçi və ya operator subyektə fərdi məlumatların məcburi şəkildə təqdim edilməsindən imtinanın hüquqi nəticələri barədə məlumat verməlidir. | H9: Fərdi məlumatların mülkiyyətçisi və operatoru (dövlət/yerli özünüidarə orqanları, hüquqi və fiziki şəxslər; şəxsi/ailə ehtiyacları istisna — 3.3) | I9: Legal | J9: on event (məlumat toplanarkən) | K9: Yüksək | L9: Rəqəmsal İnkişaf və Nəqliyyat Nazirliyi (qanunda: 'müvafiq icra hakimiyyəti orqanı'; konkret orqan Prezident fərmanları ilə müəyyən edilir) (yoxlanmalı) | M9: • 11.2.1–11.2.6 elementlərini əhatə edən məxfilik bildirişi • Bildirişin bütün toplama kanallarında (veb, mobil, kağız) yerləşdirilməsi • Məcburi məlumatlar üçün imtinanın nəticələri barədə mətn (11.3) | N9: • Məxfilik bildirişi (subyektin məlumatlandırılması) | O9: https://e-qanun.az/frameworks/19/f_19675.html
A10: PD-09 | B10: Fərdi məlumatlar | C10: Fərdi məlumatlar haqqında Qanun | D10: Maddə 5.8, 5.5, 10.1 | E10: Fərdi məlumatları itki, icazəsiz giriş, dəyişdirilmə və məhvdən qorumaq üçün texniki-təşkilati tədbirlər görün. | F10: Implement technical and organisational measures protecting personal data against loss, unauthorised access, alteration and destruction. | G10: 5.8. Mülkiyyətçi və ya operator fərdi məlumatların mühafizəsinin (o cümlədən təsadüfi və icazəsiz məhv edilməsinin, itirilməsinin, qanunsuz müdaxilənin, dəyişdirilməsinin və digər halların qarşısının alınmasının) təmin edilməsinə zəmanət verən texniki-təşkilati tədbirlər görməlidir. […] Fərdi məlumatların mühafizəsi mülkiyyətçilər və operatorlar tərəfindən təmin olunmalıdır. […] 10.1. Fərdi məlumatların toplanılması və işlənilməsi zamanı mülkiyyətçinin vəzifələri fərdi məlumatların toplanılmasının və işlənilməsinin qanuniliyini və təhlükəsizliyini təmin etməkdən ibarətdir. | H10: Fərdi məlumatların mülkiyyətçisi və operatoru (dövlət/yerli özünüidarə orqanları, hüquqi və fiziki şəxslər; şəxsi/ailə ehtiyacları istisna — 3.3) | I10: Legal | J10: ongoing | K10: Yüksək | L10: Rəqəmsal İnkişaf və Nəqliyyat Nazirliyi; mühafizə tələblərinə nəzarətdə təhlükəsizlik orqanları da iştirak edə bilər (5.9-cu maddə: tələblər 'müvafiq icra hakimiyyəti orqanı' tərəfindən müəyyən olunur) (yoxlanmalı) | M10: • Rol əsaslı giriş nəzarəti və ən az imtiyaz prinsipi • Saxlanmada və ötürmədə şifrələmə • Ehtiyat nüsxə və bərpa testləri • İllik risk qiymətləndirməsi və zəiflik skanı • Nazirlər Kabinetinin 'Fərdi məlumatların mühafizəsinə dair Tələblər'inə uyğunluq yoxlaması (5.9) | N10: • İnformasiya təhlükəsizliyi siyasəti • Girişə nəzarət və audit jurnalı proseduru • Fərdi məlumat insidentlərinə cavab proseduru | O10: https://e-qanun.az/frameworks/19/f_19675.html
A11: PD-10 | B11: Fərdi məlumatlar | C11: Fərdi məlumatlar haqqında Qanun | D11: Maddə 5.5 | E11: Fərdi məlumatlarla işləyən hər əməkdaşdan işdən çıxdıqdan sonra da qüvvədə olan yazılı məxfilik öhdəliyi alın. | F11: Obtain a written non-disclosure undertaking, surviving termination, from every staff member handling personal data. | G11: Fərdi məlumatların toplanılması, işlənilməsi və mühafizəsi sahəsində fəaliyyət göstərən fiziki şəxslər fəaliyyət müddətində və işdən çıxdıqdan sonra həmin məlumatların yayılmaması barədə yazılı iltizam verməlidirlər. | H11: Mülkiyyətçi və operator (onların fərdi məlumatlarla işləyən əməkdaşları — fiziki şəxslər) | I11: Legal | J11: on event (işə qəbul / vəzifəyə təyinat zamanı) | K11: Orta | L11: Rəqəmsal İnkişaf və Nəqliyyat Nazirliyi (qanunda: 'müvafiq icra hakimiyyəti orqanı'; konkret orqan Prezident fərmanları ilə müəyyən edilir) (yoxlanmalı) | M11: • İşə qəbul paketində məxfilik öhdəliyi forması • HR sistemində imzalanmış öhdəliklərin uçotu • İllik məxfilik təlimi | N11: • Əməkdaşların məxfilik öhdəliyi • İnformasiya təhlükəsizliyi siyasəti | O11: https://e-qanun.az/frameworks/19/f_19675.html
A12: PD-11 | B12: Fərdi məlumatlar | C12: Fərdi məlumatlar haqqında Qanun | D12: Maddə 12.1, 12.4, 12.6 | E12: Subyekt sorğularına ödənişsiz, 7 iş günü (zərurətdə +7) ərzində cavab verin; imtinanı 5 iş günü ərzində əsaslandırın. | F12: Answer data-subject requests free of charge within 7 working days (+7 if needed); justify refusals within 5 working days. | G12: 12.1. Mülkiyyətçi və ya operator ödənişsiz olaraq subyektə onun haqqında məlumatları təqdim etməli, eləcə də bu Qanunun 7.1-ci maddəsində göstərilmiş hüquqlarını təmin etməlidir. […] 12.4. Mülkiyyətçi və ya operator subyektin verdiyi sorğuya daxil olduğu gündən ən geci 7 iş günü keçənədək cavab verməlidir, bununla bağlı üçüncü şəxsə müraciət etmək zərurəti yarandıqda sorğunun icra müddəti daha 7 iş günü uzadıla bilər. […] 12.6. Mülkiyyətçi və ya operator subyektin sorğusunun icrasından qanunvericiliklə müəyyən edilmiş əsaslarla imtina etdikdə subyektə sorğusunun alındığı gündən 5 iş günü keçənədək əsaslandırılmış cavab verməlidir. | H12: Fərdi məlumatların mülkiyyətçisi və operatoru (dövlət/yerli özünüidarə orqanları, hüquqi və fiziki şəxslər; şəxsi/ailə ehtiyacları istisna — 3.3) | I12: Legal | J12: on event: müraciətdən sonra 7 iş günü (üçüncü şəxsə müraciət zərurətində +7 iş günü); imtina — 5 iş günü | K12: Yüksək | L12: Rəqəmsal İnkişaf və Nəqliyyat Nazirliyi (qanunda: 'müvafiq icra hakimiyyəti orqanı'; konkret orqan Prezident fərmanları ilə müəyyən edilir) (yoxlanmalı) | M12: • Sorğuların qeydiyyatı jurnalı və SLA izləməsi • Şəxsiyyətin yoxlanması (7.5: kağız ərizə + şəxsiyyət sənədi və ya gücləndirilmiş e-imza) • Cavabda digər şəxslərin məlumatlarının çıxarılması (12.3) • Standart cavab/imtina şablonları | N12: • Subyekt sorğularına baxılma proseduru | O12: https://e-qanun.az/frameworks/19/f_19675.html
... A82: CB-20 | B82: Mərkəzi Bank | C82: CBAR İnformasiya təhlükəsizliyi Tələbləri (14/2) | D82: Bənd 5.2.2, 5.2.3, 5.2.4, 5.2.5 | E82: Personala ildə 2 dəfə təlim, 4 dəfə maarifləndirmə; təchizatçılara ildə 2, müştərilərə rübdə 1 dəfə məlumat verin. | F82: Train staff on IS policy at least twice a year and run awareness at least four times a year; inform suppliers twice a year; educate customers at least quarterly; training programmes approved by the CEO. | G82: 5.2.2. personalı informasiya təhlükəsizliyi siyasəti və onların funksiyalarına uyğun olan qaydalarla bağlı azı ildə 2 (iki) dəfə və müvafiq sənədlərdə dəyişikliklər edildikdə növbədənkənar qaydada təlimlərə cəlb edir, habelə informasiya təhlükəsizliyi ilə əlaqədar azı ildə 4 (dörd) dəfə maarifləndirir; 5.2.3. təchizatçıları informasiya təhlükəsizliyi tələbləri ilə əlaqədar azı ildə 2 (iki) dəfə, habelə dəyişiklik edildikdə növbədənkənar qaydada məlumatlandırır; 5.2.4. müştəriləri informasiya təhlükəsizliyi ilə əlaqədar azı rübdə bir dəfə maarifləndirir; 5.2.5. informasiya təhlükəsizliyinə dair personal üçün təlim proqramları nəzarət subyektinin icra orqanının rəhbəri tərəfindən təsdiq edilir və icrasına nəzarət edilir; | H82: Banks (I kateqoriya nəzarət subyekti / Category I supervised entity; same rule also binds the other supervised entities in 1.1) | I82: Regulatory | J82: staff training semi-annual; awareness quarterly; customers quarterly; suppliers semi-annual | K82: Orta | L82: Azərbaycan Respublikasının Mərkəzi Bankı | M82: • CEO-approved IS training programme • Training attendance records • Customer awareness campaign log | N82: • IS Training and Awareness Programme | O82: https://e-qanun.az/frameworks/56/f_56708.html

Sheet Policy-lər
A1: Policy / prosedur (AZ) | B1: Policy (EN) | C1: Məqsəd | D1: Hansı maddələrdən irəli gəlir | E1: Qanun
A2: Fərdi məlumatların mühafizəsi siyasəti | B2: Personal Data Protection Policy | C2: Prinsipləri (qanunçuluq, konfidensiallıq, məqsəd məhdudluğu, minimallaşdırma, dəqiqlik), rolları və məsuliyyətləri müəyyən edən çətir sənəd. | D2: 4.1; 5.5; 9.1-9.3; 9.6; 10.1; 11.1 · PD-01; PD-04; PD-09 | E2: Azərbaycan Respublikasının "Fərdi məlumatlar haqqında" Qanunu
A3: Emal fəaliyyətlərinin reyestri proseduru | B3: Record of Processing Activities Procedure | C3: Hər emal fəaliyyəti üçün məqsəd, hüquqi əsas, kateqoriyalar, alıcılar, saxlanma və sistemləri qeydə almaq (qeydiyyat müraciətinin 15.4 məlumatlarının mənbəyi). | D3: 9.1; 9.6; 15.4 · PD-01; PD-04; PD-16 | E3: Azərbaycan Respublikasının "Fərdi məlumatlar haqqında" Qanunu
A4: Razılığın idarə edilməsi proseduru | B4: Consent Management Procedure | C4: Yazılı/e-imzalı razılığın 8.2 elementləri ilə alınması, EHİS üzərindən idarəsi, sübutun saxlanması və geri çağırmanın icrası. | D4: 8.1-8.6; 13.1; 13.3 · PD-02; PD-03; PD-13; PD-14 | E4: Azərbaycan Respublikasının "Fərdi məlumatlar haqqında" Qanunu
A5: Məxfilik bildirişi (subyektin məlumatlandırılması) | B5: Privacy Notice | C5: Toplama zamanı 11.2 və 11.3-də tələb olunan məlumatların subyektə təqdim edilməsi. | D5: 11.2; 11.3 · PD-08; PD-02 | E5: Azərbaycan Respublikasının "Fərdi məlumatlar haqqında" Qanunu
A6: Subyekt sorğularına baxılma proseduru | B6: Data Subject Request Procedure | C6: Giriş, düzəliş, məhv, qadağa və etiraz sorğularının şəxsiyyət yoxlaması ilə qəbulu və 7/5/3 iş günü müddətlərində icrası. | D6: 7.1-7.5; 12.1-12.6 · PD-11; PD-12; PD-13; PD-17 | E6: Azərbaycan Respublikasının "Fərdi məlumatlar haqqında" Qanunu
A7: Məlumatların saxlanması və məhv edilməsi siyasəti | B7: Data Retention and Destruction Policy | C7: Saxlanma müddətlərini, məqsəd bitdikdə məhvetmə/arxivləşdirmə və məhvetmə aktlarının qaydasını müəyyən etmək. | D7: 8.2.6; 9.4; 9.8; 15.6; 5.10 · PD-05; PD-06 | E7: Azərbaycan Respublikasının "Fərdi məlumatlar haqqında" Qanunu
A8: İnformasiya təhlükəsizliyi siyasəti | B8: Information Security Policy | C8: Fərdi məlumatların mühafizəsi üçün texniki-təşkilati tədbirləri və Nazirlər Kabinetinin mühafizə tələblərinə uyğunluğu təmin etmək. | D8: 5.2; 5.8; 5.9; 14.4 · PD-09; PD-10; PD-15 | E8: Azərbaycan Respublikasının "Fərdi məlumatlar haqqında" Qanunu
A9: Girişə nəzarət və audit jurnalı proseduru | B9: Access Control and Audit Logging Procedure | C9: Fərdi məlumatlara girişin məhdudlaşdırılması və 9.12 üzrə nəzarət-audit jurnallarının aparılması. | D9: 5.2; 9.12 · PD-09; PD-17 | E9: Azərbaycan Respublikasının "Fərdi məlumatlar haqqında" Qanunu
A10: Xüsusi kateqoriyalı və biometrik məlumatların emalı proseduru | B10: Special Category and Biometric Data Procedure | C10: Xüsusi kateqoriyalı və biometrik məlumatların yalnız icazə verilən hallarda, gücləndirilmiş mühafizə ilə emalı və əsas aradan qalxdıqda bloklanması/məhvi. | D10: 2.1.6; 9.5; 9.7; 9.8 · PD-06; PD-07 | E10: Azərbaycan Respublikasının "Fərdi məlumatlar haqqında" Qanunu
A11: Transsərhəd ötürmə proseduru | B11: Cross-Border Data Transfer Procedure | C11: Xaricə ötürmələrin (o cümlədən xarici bulud xidmətlərinin) adekvatlıq qiymətləndirməsi, razılıq və təhlükəsizlik tədbirləri ilə idarəsi. | D11: 14.1-14.4; 15.4.13 · PD-15 | E11: Azərbaycan Respublikasının "Fərdi məlumatlar haqqında" Qanunu
A12: Üçüncü şəxslərə məlumat verilməsi və operatorların idarə edilməsi siyasəti | B12: Third-Party Disclosure and Processor Management Policy | C12: Üçüncü şəxslərə verilmənin əsaslarını, operator (podratçı) müqavilələrini, due diligence və alıcılara bildirişləri tənzimləmək. | D12: 9.9; 10.3; 10.4; 12.5; 13.1-13.3 · PD-12; PD-14; PD-18; PD-20 | E12: Azərbaycan Respublikasının "Fərdi məlumatlar haqqında" Qanunu
... A68: Texniki zəifliklərin idarə edilməsi (vəzifələr və prosedurlar) | B68: Vulnerability and Patch Management Procedure | C68: Roles for vulnerability monitoring, patching, annual pen tests, pre-production testing. | D68: Bənd 7.18 | E68: CBAR İnformasiya təhlükəsizliyi Tələbləri (14/2), Banklarda informasiya təhlükəsizliyinin idarə edilməsi Qaydası (20/1) — LƏĞV EDİLİB

Sheet Xülasə
A1: Qanun / qayda | B1: Öhdəlik sayı | C1: Yüksək | D1: Orta | E1: Aşağı
A2: CBAR İnformasiya təhlükəsizliyi Tələbləri (14/2) | B2: =COUNTIF(Öhdəliklər!$C:$C,A2) | C2: =COUNTIFS(Öhdəliklər!$C:$C,A2,Öhdəliklər!$K:$K,"Yüksək") | D2: =COUNTIFS(Öhdəliklər!$C:$C,A2,Öhdəliklər!$K:$K,"Orta") | E2: =COUNTIFS(Öhdəliklər!$C:$C,A2,Öhdəliklər!$K:$K,"Aşağı")
A3: Elektron İmza Qanunu | B3: =COUNTIF(Öhdəliklər!$C:$C,A3) | C3: =COUNTIFS(Öhdəliklər!$C:$C,A3,Öhdəliklər!$K:$K,"Yüksək") | D3: =COUNTIFS(Öhdəliklər!$C:$C,A3,Öhdəliklər!$K:$K,"Orta") | E3: =COUNTIFS(Öhdəliklər!$C:$C,A3,Öhdəliklər!$K:$K,"Aşağı")
A4: Fərdi məlumatlar haqqında Qanun | B4: =COUNTIF(Öhdəliklər!$C:$C,A4) | C4: =COUNTIFS(Öhdəliklər!$C:$C,A4,Öhdəliklər!$K:$K,"Yüksək") | D4: =COUNTIFS(Öhdəliklər!$C:$C,A4,Öhdəliklər!$K:$K,"Orta") | E4: =COUNTIFS(Öhdəliklər!$C:$C,A4,Öhdəliklər!$K:$K,"Aşağı")
A5: KİI Qaydaları (NK № 229) / İnformasiya Qanunu V-I fəsil | B5: =COUNTIF(Öhdəliklər!$C:$C,A5) | C5: =COUNTIFS(Öhdəliklər!$C:$C,A5,Öhdəliklər!$K:$K,"Yüksək") | D5: =COUNTIFS(Öhdəliklər!$C:$C,A5,Öhdəliklər!$K:$K,"Orta") | E5: =COUNTIFS(Öhdəliklər!$C:$C,A5,Öhdəliklər!$K:$K,"Aşağı")
A6: İnformasiya Qanunu | B6: =COUNTIF(Öhdəliklər!$C:$C,A6) | C6: =COUNTIFS(Öhdəliklər!$C:$C,A6,Öhdəliklər!$K:$K,"Yüksək") | D6: =COUNTIFS(Öhdəliklər!$C:$C,A6,Öhdəliklər!$K:$K,"Orta") | E6: =COUNTIFS(Öhdəliklər!$C:$C,A6,Öhdəliklər!$K:$K,"Aşağı")
A7: Cəmi | B7: =SUM(B2:B6) | C7: =SUM(C2:C6) | D7: =SUM(D2:D6) | E7: =SUM(E2:E6)

Sheet Qeydlər
A1: Fayl | B1: Qeyd
A2: personal_data | B2: Mətn rəsmi Hüquqi İnformasiya Mərkəzinin e-qanun.az portalından (framework 19675, htmlUrl) götürülüb; bütün verbatim_az sitatları skript vasitəsilə həmin mətnə qarşı hərfi-hərfinə yoxlanılıb ('[…]' buraxılmış hissəni göstərir; '[3]' kimi işarələr mənbədəki dəyişiklik qeydləridir). Konsolidə mətndə son dəyişiklik 28.06.2024 № 1193-VIQD-dir; ondan sonrakı dəyişikliklər (əgər varsa) portalda əks olunmayıbsa, burada yoxdur — tətbiqdən əvvəl yoxlanmalı. Qanun nəzarət orqanını yalnız 'müvafiq icra hakimiyyəti orqanı' kimi göstərir. 'Rəqəmsal İnkişaf və Nəqliyyat Nazirliyi' göstəricisi qanunun mətnindən deyil, tətbiq fərmanlarından (4 iyun 2010 № 275 və sonrakı dəyişikliklər) və nazirliyin əsasnaməsindən irəli gələn cari təcrübəyə əsaslanır — (yoxlanmalı). Mühafizə tələblərinə (5.9) nəzarətdə təhlükəsizlik orqanlarının rolu da yoxlanmalıdır. Qanunda GDPR-dəki kimi pozuntu (breach) barədə bildiriş öhdəliyi, DPO təyinatı və ya DPIA tələbi yoxdur; 'Fərdi məlumat insidentlərinə cavab proseduru' ən yaxşı təcrübə kimi əlavə edilib. 9.14 (lisenziya) tələbinin praktiki tətbiqi 'Lisenziyalar və icazələr haqqında' Qanunun hazırkı siyahısına qarşı yoxlanmalıdır. Sertifikatlaşdırma və dövlət ekspertizası (6.0.6, 6.0.8, 7.1.9, 11.2.4) qanunda dövlət tənzimləməsi forması kimi göstərilir, lakin mülkiyyətçiyə birbaşa 'sertifikat almalıdır' öhdəliyi ayrıca maddədə yoxdur; ona görə ayrıca öhdəlik kimi daxil edilməyib (yalnız 11.2.4 üzrə məlumatlandırma). Daxil edilməyən, lakin niş hallarda tətbiq olunan müddəalar: 5.7 (ümumi istifadəli sistemlərə açıq mənbələrdən daxil edilən məlumatlar barədə subyektə bildiriş), 8.5 (açıq kateqoriyanı sübut etmək), 9.13 (elmi/statistik tədqiqatda adsızlaşdırma), 10.5 (əməliyyat-axtarış tədbirlərinə şərait), 15.6 (qeydiyyat ləğv edildikdə məlumatların məhvi), 18.3 (müxtəlif mülkiyyətçilərin sistemlərinin birləşdirilməsinin qadağası). Məsuliyyət (19-cu maddə) ümumi istinad xarakterlidir; konkret cərimələr İnzibati Xətalar Məcəlləsi və Cinayət Məcəlləsində (məs. şəxsi həyatın toxunulmazlığı) müəyyən edilir — risk səviyyələri subyektiv qiymətləndirmədir. Mənbə mətndə qeyd: [9]-cu dəyişiklik qeydi 2018-ci il qanunu ilə 13.2-1-dən 'birbaşa və ya' sözlərinin çıxarıldığını bildirir, lakin konsolidə mətndə bu sözlər hələ də var — portalın redaksiya uyğunsuzluğu (bu kitabxanadakı öhdəliklərə təsir etmir).
A3: info_esign_kii | B3: SOURCES: All verbatim quotes were extracted programmatically from official consolidated texts on e-qanun.az (Ministry of Justice legal database) fetched 2026-10-15: info law framework 3525, e-signature law 5916, KII Rules (Cabinet Decision 229) 54651. Editorial footnote markers like “[58]” were removed from quotes; otherwise text is unchanged. Articles 1–21 of the info law have no sub-numbering, so references use “Maddə X (n-ci hissə)”. KII Rules were cross-checked against the original publication in the “Azərbaycan” newspaper (20.07.2023); the e-qanun text includes the 02.12.2023 (NK № 431) amendments. nk.gov.az, azertag.az and meclis.gov.az were unreachable from this environment (connection reset / Cloudflare block). KII STATUS: KII rules are in force (not drafts): Info law ch. V-I (Art. 20-1 – 20-6, added by 539-VIQD of 27.05.2022, amended by 861-VIQD of 11.04.2023), Cabinet Decision № 229 (17.07.2023), Register rules № 230 (17.07.2023, not fetched), KII object list № 501 (29.11.2024, not fetched — whether a given company is a KII subject depends on this list). Competent authority: State Security Service (DTX) / National Cyber Centre, jointly with XRİTDX for state bodies and state-owned legal entities (Decree № 1315). Micro, small and medium enterprises are excluded from the definition of KII subject (Art. 2). For private (non-state) entrepreneurs, compliance checks are conducted remotely, without site visits (Law 20-6.4; Rules 9.7). 2026 CYBERSECURITY AMENDMENTS: Law 454-VIIQD of 14.07.2026 (published 10.08.2026) is already incorporated in the consolidated info-law text and in force (no deferred entry-into-force clause in the text; implemented by Decree № 761 of 10.08.2026). It adds ch. V-II (Art. 20-7 – 20-12): National CERT/SOC, sectoral CERTs, CERT/SOC registry, “information infrastructure performing socially significant functions”, digital forensics, a general duty on ALL information-infrastructure subjects to report incidents immediately to the National CERT, 24h/5-working-day request deadlines, and .az domain sanctions. PENDING / NOT YET ISSUED (not included as obligations): (1) general cybersecurity requirements for “information infrastructure performing socially significant functions” (Art. 20-7.5) — Cabinet must approve within 9 months of Decree 761 (≈ by May 2027); RİNN to submit draft within 8 months (Cabinet order 613s, 17.08.2026); sector-specific requirements to follow from sector regulators, and for financial-market entities from the Central Bank; (2) lists of socially-significant-infrastructure subjects (Art. 20-7.3) to be set by sector regulators; (3) rules on monitoring/audit/security opinions for state information resources (Art. 14, 8th part) and security rules for state bodies’ infrastructure (Art. 20-7.10); (4) KII-related CERTs/SOCs must be entered in the registry within ~1 year per Decree 761 §§4–5. The KII Rules (2023) have not (per e-qanun as of 2026-10-15) been updated to reflect 454-VIIQD; terminology (Milli kibermərkəz vs. Milli CERT) may change. (5) Law 431-VIIQD of 30.06.2026 (social-network platform age verification, new Art. 13-4/13-5, renumbering current 13-4 to 13-6) enters into force 05.08.2027 — relevant only to platform providers; not included. CAVEATS: Authorities marked “(yoxlanmalı)” could not be confirmed from the fetched implementing acts. The certification body under info-law Art. 16 was not identified. Liability amounts are set in the Code of Administrative Offences (not reviewed). Several obligations (ES-11, ES-12, INF-14, KII-15) apply only to specific roles (CA, intermediary, CERT/SOC operator, MSSP). The e-signature law Art. 34.2 has a textual defect on e-qanun (“İstifadə Tərkibində …”) and was not used. Frequencies such as “at least annual” in INF-09 are recommendations where the law sets none. This is a compliance-library sample, not legal advice.
A4: cbar | B4: 1) Act (a) — CBAR Board decision 20/1 of 14 July 2021 (number/date verified on official PDF and e-qanun) approving 'Banklarda informasiya təhlükəsizliyinin idarə edilməsi Qaydası' — has NO current version: its Part 1 (the Rules) was repealed by Decision 14/2 from 09.04.2025. 2) Act (b) verified: Decision 14/2 of 28.03.2024 'Maliyyə bazarlarında fəaliyyətinə nəzarət edilən subyektlərdə informasiya təhlükəsizliyinin təmin edilməsinə dair Tələblər' — registered 08.04.2024 (code 23202403280142), in force from 09.04.2025 (one year after publication). It applies to banks (Category I) and other supervised entities, so ALL obligations here are drawn from 14/2. 3) No extra act included: no separate CBAR outsourcing/cloud or IT-risk rule for banks was located with official text in this pass; note 14/2 itself contains cloud (4.10), supplier (4.9) and outsourced development (7.26.7) requirements. Other possibly relevant CBAR acts not reviewed: 'Banklarda risklərin idarə olunması haqqında Qaydalar', 'Gücləndirilmiş müştəri autentifikasiyasının tətbiqi Qaydası' (12/2, 13.03.2024), electronic banking methodological guidance. 4) verbatim_az fields are exact paragraph texts extracted programmatically from the e-qanun HTML (cp1251-decoded, whitespace normalised); multiple paragraphs are joined by newlines. Paragraph 8.3/8.4 say 'bu Qaydaya ... Əlavədə' (sic) in the official text. 5) Category-specific carve-outs (1.4, 1.5) do not affect banks. 6) obligation_az/en and risk ratings are editorial summaries, not legal text; not legal advice. 7) cbar.az also hosts a Board-approved 2026 regulation on CBAR's own IS/cyber/digital-fraud department (internal, not a bank obligation) — excluded.
